PheonixAppAPI/__init__.py
PheonixAppAPI/api.py
PheonixAppAPI/bin_worker.py
PheonixAppAPI/main.py
PheonixAppAPI/Scripts/RESOURCES.py
PheonixAppAPI/Scripts/__init__.py
PheonixAppAPI/Scripts/post_install.py
PheonixAppAPI/apis/Cipher.py
PheonixAppAPI/apis/FileManager.py
PheonixAppAPI/apis/ModuleAPI.py
PheonixAppAPI/apis/PACI.py
PheonixAppAPI/apis/__init__.py
PheonixAppAPI/apis/Modules/__init__.py
PheonixAppAPI/apis/Modules/Pre/__init__.py
PheonixAppAPI/apis/Modules/Pre/PheonixExceptions/Exceptions.py
PheonixAppAPI/apis/Modules/Pre/PheonixExceptions/__init__.py
PheonixAppAPI/apis/Modules/Pre/PheonixJson/Json.py
PheonixAppAPI/apis/Modules/Pre/PheonixJson/Psaaf.py
PheonixAppAPI/apis/Modules/Pre/PheonixJson/__init__.py
PheonixAppAPI/apis/Modules/Pre/phardwareitk/Dependencies.py
PheonixAppAPI/apis/Modules/Pre/phardwareitk/LIB.py
PheonixAppAPI/apis/Modules/Pre/phardwareitk/__init__.py
PheonixAppAPI/apis/Modules/Pre/phardwareitk/CLI/__init__.py
PheonixAppAPI/apis/Modules/Pre/phardwareitk/CLI/cliToolKit.py
PheonixAppAPI/apis/Modules/Pre/phardwareitk/ErrorSystem/ErrorSystem.py
PheonixAppAPI/apis/Modules/Pre/phardwareitk/ErrorSystem/__init__.py
PheonixAppAPI/apis/Modules/Pre/phardwareitk/Extensions/HyperIn.py
PheonixAppAPI/apis/Modules/Pre/phardwareitk/Extensions/HyperOut.py
PheonixAppAPI/apis/Modules/Pre/phardwareitk/Extensions/HyperPython.py
PheonixAppAPI/apis/Modules/Pre/phardwareitk/Extensions/__init__.py
PheonixAppAPI/apis/Modules/Pre/phardwareitk/FileSystem/FileSystem.py
PheonixAppAPI/apis/Modules/Pre/phardwareitk/FileSystem/__init__.py
PheonixAppAPI/apis/Modules/Pre/phardwareitk/GUI/__init__.py
PheonixAppAPI/apis/Modules/Pre/phardwareitk/GUI/gui.py
PheonixAppAPI/apis/Modules/Pre/phardwareitk/GUI/gui_sdl.py
PheonixAppAPI/apis/Modules/Pre/phardwareitk/HGame/__init__.py
PheonixAppAPI/apis/Modules/Pre/phardwareitk/ModuleController/__init__.py
PheonixAppAPI/apis/Modules/Pre/phardwareitk/ModuleController/main.py
PheonixAppAPI/apis/Modules/Pre/phardwareitk/PLTEC/ASM.py
PheonixAppAPI-0.2.7.1.dist-info/LICENCE
PheonixAppAPI-0.2.7.1.dist-info/METADATA
PheonixAppAPI-0.2.7.1.dist-info/WHEEL
PheonixAppAPI-0.2.7.1.dist-info/top_level.txt
PheonixAppAPI-0.2.7.1.dist-info/RECORD
