Metadata-Version: 2.1
Name: PheonixAppAPI
Version: 0.2.7.1
Summary: Pheonix App 1.0 is a powerful Python application designed to streamline various tasks, from managing files to playing mini-games. This module is a API for this APP. NOTE: updates will come for the app. For Showcases view AkshobhyaEverything channel or the Pheonix Studios Developer channel
Author-email: Pheonix Studios <pheonix.community.mail@gmail.com>, Akshobhya Sasun <akshobhyasasun@gmail.com>, Aarav Nayak <legoheroaarav@gmail.com>
Project-URL: Homepage, https://github.com/AkshuDev/PheonixAppAPI
Project-URL: Issues, https://github.com/AkshuDev/PheonixAppAPI/issues
Project-URL: Website, https://paperecahange.wixsite.com/pheonixstudios
Project-URL: Source, https://github.com/AkshuDev/PheonixAppAPI
Classifier: Programming Language :: Python :: 3
Classifier: License :: OSI Approved :: MIT License
Classifier: Operating System :: OS Independent
Requires-Python: >=3.8
License-File: LICENCE
Requires-Dist: wikipedia
Requires-Dist: xlsxwriter
Requires-Dist: requests
Requires-Dist: cryptography
Requires-Dist: PyCryptodome
Requires-Dist: sympy
Requires-Dist: pysdl2
Requires-Dist: pysdl2-dll
Requires-Dist: PyOpenGL
